silicon_compiler_from_scratch/rtl/counter4.v
// Chapter 1, running example B: a 4-bit counter, the smallest circuit with MEMORY (four flip-flops).
//   Every rising clock edge: if rst is 1, q becomes 0 (reset wins over everything); otherwise, if en is 1, q increases by one, wrapping from 15 to 0; otherwise q holds.
//   wrap is 1 during the cycle in which the next edge will wrap q from 15 to 0 (a combinational output: it depends on q and en right now).
module counter4 (input clk, input rst, input en, output reg [3:0] q, output wrap);
    assign wrap = en && (q == 4'd15);
    always @(posedge clk) begin
        if (rst) q <= 4'd0;
        else if (en) q <= q + 4'd1;
    end
endmodule

silicon_compiler_from_scratch/tb/counter4_wave_tb.v
// Chapter 1, running example B: a short, readable run of the counter, dumped as a waveform: reset, count to a wrap, hold, reset while enabled.
`timescale 1ns/1ns
module counter4_wave_tb;
    reg clk = 0, rst = 0, en = 0; wire [3:0] q; wire wrap; integer i;
    counter4 dut (.clk(clk), .rst(rst), .en(en), .q(q), .wrap(wrap));
    always #5 clk = ~clk;                                    // period 10: rising edges at 5, 15, 25, ...
    initial begin
        $dumpfile("out/counter4.vcd"); $dumpvars(0, counter4_wave_tb);
        rst = 1; en = 0; #20; rst = 0; en = 1; #170;       // reset for two edges, then count: passes 15 -> 0 once
        en = 0; #40; en = 1; #30; rst = 1; #10; rst = 0; #30;   // hold four edges; count; reset while enabled; count again
        $finish;
    end
endmodule

silicon_compiler_from_scratch/out/counter4.vcd
$date
	Thu Oct  8 14:31:14 2026
$end
$version
	Icarus Verilog
$end
$timescale
	1ns
$end
$scope module counter4_wave_tb $end
$var wire 1 ! wrap $end
$var wire 4 " q [3:0] $end
$var reg 1 # clk $end
$var reg 1 $ en $end
$var reg 1 % rst $end
$scope module dut $end
$var wire 1 # clk $end
$var wire 1 $ en $end
$var wire 1 % rst $end
$var wire 1 ! wrap $end
$var reg 4 & q [3:0] $end
$upscope $end
$upscope $end
$enddefinitions $end
$comment Show the parameter values. $end
$dumpall
$end
#0
$dumpvars
bx &
1%
0$
0#
bx "
0!
$end
#5
b0 "
b0 &
1#
#10
0#
#15
1#
#20
0#
1$
0%
#25
b1 "
b1 &
1#
#30
0#
#35
b10 "
b10 &
1#
#40
0#
#45
b11 "
b11 &
1#
#50
0#
#55
b100 "
b100 &
1#
#60
0#
#65
b101 "
b101 &
1#
#70
0#
#75
b110 "
b110 &
1#
#80
0#
#85
b111 "
b111 &
1#
#90
0#
#95
b1000 "
b1000 &
1#
#100
0#
#105
b1001 "
b1001 &
1#
#110
0#
#115
b1010 "
b1010 &
1#
#120
0#
#125
b1011 "
b1011 &
1#
#130
0#
#135
b1100 "
b1100 &
1#
#140
0#
#145
b1101 "
b1101 &
1#
#150
0#
#155
b1110 "
b1110 &
1#
#160
0#
#165
1!
b1111 "
b1111 &
1#
#170
0#
#175
0!
b0 "
b0 &
1#
#180
0#
#185
b1 "
b1 &
1#
#190
0#
0$
#195
1#
#200
0#
#205
1#
#210
0#
#215
1#
#220
0#
#225
1#
#230
0#
1$
#235
b10 "
b10 &
1#
#240
0#
#245
b11 "
b11 &
1#
#250
0#
#255
b100 "
b100 &
1#
#260
0#
1%
#265
b0 "
b0 &
1#
#270
0#
0%
#275
b1 "
b1 &
1#
#280
0#
#285
b10 "
b10 &
1#
#290
0#
#295
b11 "
b11 &
1#
