silicon_compiler_from_scratch/rtl/ripple.v
`timescale 1ns/1ns
// Chapter 1, running example A: the 4-bit ripple-carry adder again, but with a delay of one time unit in every full adder, so that a simulator shows the carry rippling from stage to stage.
// The delays exist only in simulation (`assign #1`); synthesis ignores them. Real gates are not instantaneous, and this is the simplest way to see what that does.
module fa_delay (input a, input b, input cin, output sum, output cout);
    assign #1 sum  = a ^ b ^ cin;
    assign #1 cout = (a & b) | (cin & (a ^ b));
endmodule
module ripple4 (input [3:0] a, input [3:0] b, input cin, output [3:0] sum, output cout);
    wire [4:0] c; assign c[0] = cin;
    genvar i;
    generate for (i = 0; i < 4; i = i + 1) begin : stage
        fa_delay fa (.a(a[i]), .b(b[i]), .cin(c[i]), .sum(sum[i]), .cout(c[i+1]));
    end endgenerate
    assign cout = c[4];
endmodule

silicon_compiler_from_scratch/tb/ripple_tb.v
// Chapter 1, running example A: apply 0111 + 0001 (the carry has to travel through all four stages) and dump every signal change to a VCD file, a standard waveform format.
`timescale 1ns/1ns
module ripple_tb;
    reg [3:0] a, b; reg cin; wire [3:0] sum; wire cout; wire [4:0] c = {dut.stage[3].fa.cout, dut.stage[2].fa.cout, dut.stage[1].fa.cout, dut.stage[0].fa.cout, cin};
    ripple4 dut (.a(a), .b(b), .cin(cin), .sum(sum), .cout(cout));
    initial begin
        $dumpfile("out/ripple.vcd"); $dumpvars(0, ripple_tb);
        a = 4'b0000; b = 4'b0000; cin = 0; #10;
        a = 4'b0111; b = 4'b0001; #10;           // 7 + 1: the carry ripples through stages 0, 1, 2
        a = 4'b1111; b = 4'b0001; #10;           // 15 + 1: through all four, out of the top
        $finish;
    end
endmodule

silicon_compiler_from_scratch/out/ripple.vcd
$date
	Thu Oct  8 14:30:50 2026
$end
$version
	Icarus Verilog
$end
$timescale
	1ns
$end
$scope module ripple_tb $end
$var wire 4 ! sum [3:0] $end
$var wire 1 " cout $end
$var wire 5 # c [4:0] $end
$var reg 4 $ a [3:0] $end
$var reg 4 % b [3:0] $end
$var reg 1 & cin $end
$scope module dut $end
$var wire 4 ' a [3:0] $end
$var wire 4 ( b [3:0] $end
$var wire 1 & cin $end
$var wire 4 ) sum [3:0] $end
$var wire 1 " cout $end
$var wire 5 * c [4:0] $end
$scope begin stage[0] $end
$var parameter 2 + i $end
$scope module fa $end
$var wire 1 , a $end
$var wire 1 - b $end
$var wire 1 . cin $end
$var wire 1 / cout $end
$var wire 1 0 sum $end
$upscope $end
$upscope $end
$scope begin stage[1] $end
$var parameter 2 1 i $end
$scope module fa $end
$var wire 1 2 a $end
$var wire 1 3 b $end
$var wire 1 4 cin $end
$var wire 1 5 cout $end
$var wire 1 6 sum $end
$upscope $end
$upscope $end
$scope begin stage[2] $end
$var parameter 3 7 i $end
$scope module fa $end
$var wire 1 8 a $end
$var wire 1 9 b $end
$var wire 1 : cin $end
$var wire 1 ; cout $end
$var wire 1 < sum $end
$upscope $end
$upscope $end
$scope begin stage[3] $end
$var parameter 3 = i $end
$scope module fa $end
$var wire 1 > a $end
$var wire 1 ? b $end
$var wire 1 @ cin $end
$var wire 1 A cout $end
$var wire 1 B sum $end
$upscope $end
$upscope $end
$upscope $end
$upscope $end
$enddefinitions $end
$comment Show the parameter values. $end
$dumpall
b11 =
b10 7
b1 1
b0 +
$end
#0
$dumpvars
xB
xA
x@
0?
0>
x<
x;
x:
09
08
x6
x5
x4
03
02
x0
x/
0.
0-
0,
bx0 *
bx )
b0 (
b0 '
0&
b0 %
b0 $
bx0 #
x"
bx !
$end
#1
04
0:
0@
0"
0/
05
0;
b0 *
b0 #
0A
bx0 !
bx0 )
00
#2
06
0<
b0 !
b0 )
0B
#10
1-
1,
12
18
b1 %
b1 (
b111 $
b111 '
#11
14
b10 *
b10 #
1/
16
b110 !
b110 )
1<
#12
1:
b110 *
b110 #
15
b100 !
b100 )
06
#13
1@
b1110 *
b1110 #
1;
b0 !
b0 )
0<
#14
b1000 !
b1000 )
1B
#20
1>
b1111 $
b1111 '
#21
1"
b11110 *
b11110 #
1A
b0 !
b0 )
0B
